{"/_app":"pages/_app.js","/_error":"pages/_error.js","/analytics":"pages/analytics.html","/admin":"pages/admin.html","/commissions":"pages/commissions.html","/customers":"pages/customers.html","/dashboard":"pages/dashboard.html","/email-preview":"pages/email-preview.html","/inbox":"pages/inbox.html","/life-crosssell":"pages/life-crosssell.html","/quotes":"pages/quotes.html","/":"pages/index.html","/natgen-test":"pages/natgen-test.html","/retention":"pages/retention.html","/survey/[id]":"pages/survey/[id].html","/sales":"pages/sales.html","/statements":"pages/statements.html","/timeclock":"pages/timeclock.html","/api/nonpay-upload":"pages/api/nonpay-upload.js","/_document":"pages/_document.js","/404":"pages/404.html"}